{
    "happy": ["#fe9", "#e4bf00"],
    "sad": ["#99a8de", "#1d2c5c"],
    "surprise": ["#fe9", "#cc4000"],
    "neutral": ["#98e6b8", "#14552f"],
    "angry": ["#ff6057", "#7a0600"],
    "disgust": ["#ff6057", "#7a0600"],
    "fear": ["#97a3af", "#353d45"],
    "feeling frustrated": ["#ff6057", "#7a0600"],
    "finding peace": ["#ff6057", "#7a0600"],
    "just angry": ["#ff6057", "#7a0600"],
    "anti anxiety": ["#97a3af", "#353d45"],
    "focus": ["#97a3af", "#353d45"],
    "relax": ["#97a3af", "#353d45"],
    "chill": ["#98e6b8", "#14552f"],
    "instrumental": ["#98e6b8", "#14552f"],
    "meditation": ["#98e6b8", "#14552f"],
    "party vibes": ["#fe9", "#e4bf00"],
    "beach vibes": ["#fe9", "#e4bf00"],
    "happy vibes": ["#fe9", "#e4bf00"],
    "feeling nostalgic": ["#fe9", "#cc4000"],
    "anything": ["#fe9", "#cc4000"],
    "niche": ["#fe9", "#cc4000"],
    "finding comfort": ["#99a8de", "#1d2c5c"],
    "heartbroken": ["#99a8de", "#1d2c5c"],
    "just sad": ["#99a8de", "#1d2c5c"]
}